pms_inference_engine/__init__.py
pms_inference_engine/_const.py
pms_inference_engine/_dependency.py
pms_inference_engine/_engine.py
pms_inference_engine/_processor_factory.py
pms_inference_engine/_processor_pool.py
pms_inference_engine/_ray_processor.py
pms_inference_engine/_sap_processor.py
pms_inference_engine/data_struct/__init__.py
pms_inference_engine/data_struct/_engine_io_data.py
pms_inference_engine/interface/__init__.py
pms_inference_engine/interface/_i_engine_processor.py
pms_inference_engine/interface/_i_engine_processor_pool.py
pms_inference_engine/utility/__init__.py
pms_inference_engine/utility/_common.py
pms_inference_engine/utility/_ray.py
pms_inference_engine-2.0.0.dist-info/METADATA
pms_inference_engine-2.0.0.dist-info/WHEEL
pms_inference_engine-2.0.0.dist-info/RECORD
