Metadata-Version: 2.3
Name: pms-inference-engine
Version: 2.0.0
Summary: Inference Engine for pms
Author: HyeongSeok Kim
Author-email: tiryul@gmail.com
Requires-Python: ==3.12.*
Classifier: Programming Language :: Python :: 3
Classifier: Programming Language :: Python :: 3.12
Requires-Dist: loguru
Requires-Dist: numpy
Requires-Dist: ray[serve] (==2.40)
Requires-Dist: uvloop
